e2cnn/__about__.py
e2cnn/__init__.py
e2cnn/diffops/__init__.py
e2cnn/diffops/basis.py
e2cnn/diffops/irreps_basis.py
e2cnn/diffops/r2.py
e2cnn/diffops/steerable_basis.py
e2cnn/diffops/utils.py
e2cnn/group/__init__.py
e2cnn/group/group.py
e2cnn/group/irrep.py
e2cnn/group/representation.py
e2cnn/group/utils.py
e2cnn/group/groups/__init__.py
e2cnn/group/groups/cyclicgroup.py
e2cnn/group/groups/dihedralgroup.py
e2cnn/group/groups/factory.py
e2cnn/group/groups/o2group.py
e2cnn/group/groups/so2group.py
e2cnn/gspaces/__init__.py
e2cnn/gspaces/gspace.py
e2cnn/gspaces/r2/__init__.py
e2cnn/gspaces/r2/flip2d_on_r2.py
e2cnn/gspaces/r2/fliprot2d_on_r2.py
e2cnn/gspaces/r2/general_r2.py
e2cnn/gspaces/r2/rot2d_on_r2.py
e2cnn/gspaces/r2/trivial_on_r2.py
e2cnn/gspaces/r2/utils.py
e2cnn/kernels/__init__.py
e2cnn/kernels/basis.py
e2cnn/kernels/irreps_basis.py
e2cnn/kernels/r2.py
e2cnn/kernels/steerable_basis.py
e2cnn/kernels/utils.py
e2cnn/nn/__init__.py
e2cnn/nn/field_type.py
e2cnn/nn/geometric_tensor.py
e2cnn/nn/init.py
e2cnn/nn/modules/__init__.py
e2cnn/nn/modules/branching_module.py
e2cnn/nn/modules/disentangle_module.py
e2cnn/nn/modules/equivariant_module.py
e2cnn/nn/modules/identity_module.py
e2cnn/nn/modules/masking_module.py
e2cnn/nn/modules/merge_module.py
e2cnn/nn/modules/module_list.py
e2cnn/nn/modules/multiple_module.py
e2cnn/nn/modules/r2upsampling.py
e2cnn/nn/modules/reshuffle_module.py
e2cnn/nn/modules/restriction_module.py
e2cnn/nn/modules/sequential_module.py
e2cnn/nn/modules/utils.py
e2cnn/nn/modules/batchnormalization/__init__.py
e2cnn/nn/modules/batchnormalization/gnorm.py
e2cnn/nn/modules/batchnormalization/induced_norm.py
e2cnn/nn/modules/batchnormalization/inner.py
e2cnn/nn/modules/batchnormalization/norm.py
e2cnn/nn/modules/dropout/__init__.py
e2cnn/nn/modules/dropout/field.py
e2cnn/nn/modules/dropout/pointwise.py
e2cnn/nn/modules/invariantmaps/__init__.py
e2cnn/nn/modules/invariantmaps/gpool.py
e2cnn/nn/modules/invariantmaps/induced_norm.py
e2cnn-0.2.2.dist-info/LICENSE
e2cnn-0.2.2.dist-info/METADATA
e2cnn-0.2.2.dist-info/WHEEL
e2cnn-0.2.2.dist-info/top_level.txt
e2cnn-0.2.2.dist-info/RECORD
