Metadata-Version: 2.1
Name: e2cnn
Version: 0.2.2
Summary: E(2)-Equivariant CNNs Library for PyTorch
Home-page: https://github.com/QUVA-Lab/e2cnn
Download-URL: https://github.com/QUVA-Lab/e2cnn/archive/v0.2.2.tar.gz
Author: Gabriele Cesa, Maurice Weiler
Author-email: cesa.gabriele@gmail.com
License: BSD 3-Clause Clear
Keywords: pytorch,cnn,convolutional-networksequivariant,isometries
Platform: UNKNOWN
Requires-Python: >=3.7
License-File: LICENSE
Requires-Dist: torch
Requires-Dist: numpy
Requires-Dist: scipy
Requires-Dist: sympy
